avaframe/RELEASE-VERSION.txt
avaframe/__init__.py
avaframe/avaframeCfg.ini
avaframe/runAna4ProbAna.py
avaframe/runAna5DFAPathGeneration.py
avaframe/runCom1DFA.py
avaframe/runCom2AB.py
avaframe/runCom4FlowPy.py
avaframe/runCom5SnowSlide.py
avaframe/runCom6RockAvalanche.py
avaframe/runCom6Scarp.py
avaframe/runIn1RelInfo.py
avaframe/runOperational.py
avaframe/runPlotCom1DFA.py
avaframe/runProbAnalysisOnly.py
avaframe/runStandardTestsCom1DFA.py
avaframe/runTmp1Ex.py
avaframe/runUpdateBenchmarkTestsCom1DFA.py
avaframe/version.py
avaframe/ana1Tests/FPtest.py
avaframe/ana1Tests/__init__.py
avaframe/ana1Tests/analysisTools.py
avaframe/ana1Tests/damBreak.py
avaframe/ana1Tests/energyLineTest.py
avaframe/ana1Tests/energyLineTestCfg.ini
avaframe/ana1Tests/rotationTest.py
avaframe/ana1Tests/rotationTestCfg.ini
avaframe/ana1Tests/simiSolTest.py
avaframe/ana1Tests/testUtilities.py
avaframe/ana3AIMEC/__init__.py
avaframe/ana3AIMEC/aimecTools.py
avaframe/ana3AIMEC/ana3AIMEC.py
avaframe/ana3AIMEC/ana3AIMECCfg.ini
avaframe/ana3AIMEC/dfa2Aimec.py
avaframe/ana4Stats/__init__.py
avaframe/ana4Stats/getStats.py
avaframe/ana4Stats/getStatsCfg.ini
avaframe/ana4Stats/probAna.py
avaframe/ana4Stats/probAnaCfg.ini
avaframe/ana5Utils/DFAPathGeneration.py
avaframe/ana5Utils/DFAPathGenerationCfg.ini
avaframe/ana5Utils/__init__.py
avaframe/ana5Utils/distanceTimeAnalysis.py
avaframe/ana5Utils/distanceTimeAnalysisCfg.ini
avaframe/com1DFA/DFAToolsCython.c
avaframe/com1DFA/DFAToolsCython.cp311-win_amd64.pyd
avaframe/com1DFA/DFAToolsCython.pxd
avaframe/com1DFA/DFAToolsCython.pyx
avaframe/com1DFA/DFAfunctionsCython.c
avaframe/com1DFA/DFAfunctionsCython.cp311-win_amd64.pyd
avaframe/com1DFA/DFAfunctionsCython.pxd
avaframe/com1DFA/DFAfunctionsCython.pyx
avaframe/com1DFA/DFAtools.py
avaframe/com1DFA/__init__.py
avaframe/com1DFA/checkCfg.py
avaframe/com1DFA/com1DFA.py
avaframe/com1DFA/com1DFACfg.ini
avaframe/com1DFA/com1DFATools.py
avaframe/com1DFA/damCom1DFA.c
avaframe/com1DFA/damCom1DFA.cp311-win_amd64.pyd
avaframe-1.13.2.dist-info/licenses/LICENSE.txt
avaframe-1.13.2.dist-info/METADATA
avaframe-1.13.2.dist-info/WHEEL
avaframe-1.13.2.dist-info/top_level.txt
avaframe-1.13.2.dist-info/RECORD
