Metadata-Version: 2.4
Name: avaframe
Version: 1.13.2
Summary: The Open Avalanche Framework
Author-email: AvaFrame Contributors <felix@avaframe.org>
License-Expression: EUPL-1.2
Project-URL: Homepage, http://avaframe.org
Classifier: Development Status :: 5 - Production/Stable
Classifier: Intended Audience :: Science/Research
Classifier: Programming Language :: Python :: 3.9
Classifier: Programming Language :: Python :: 3.10
Classifier: Programming Language :: Python :: 3.11
Classifier: Programming Language :: Python :: 3.12
Classifier: Programming Language :: Python :: 3.13
Requires-Python: <3.14,>=3.9
License-File: LICENSE.txt
Requires-Dist: numpy<2.0
Requires-Dist: salib<1.5.1
Requires-Dist: pyshp<3.0
Requires-Dist: matplotlib
Requires-Dist: scipy
Requires-Dist: cmcrameri
Requires-Dist: seaborn
Requires-Dist: cython
Requires-Dist: pandas
Requires-Dist: shapely
Requires-Dist: configUpdater
Requires-Dist: tabulate
Requires-Dist: deepdiff
Requires-Dist: deepmerge
Requires-Dist: psutil
Requires-Dist: rasterio
Requires-Dist: contextily
Requires-Dist: geopandas
Requires-Dist: fiona
Dynamic: license-file
